lacdkeras/__init__.py
lacdkeras/keras.py
lacdkeras-1.0.0.3.dist-info/LICENSE
lacdkeras-1.0.0.3.dist-info/METADATA
lacdkeras-1.0.0.3.dist-info/WHEEL
lacdkeras-1.0.0.3.dist-info/top_level.txt
lacdkeras-1.0.0.3.dist-info/RECORD
