Metadata-Version: 2.1
Name: lacdkeras
Version: 1.0.0.3
Summary: ncku AI camp
Author: HuangTeEn
Author-email: qaz910048@gmail.com
License: MIT
Keywords: Keras,Teach,lacd
License-File: LICENSE
